Metadata-Version: 2.1
Name: poobah
Version: 0.0.1
Summary: Analytical wisdom and guidance
License: BSD-3-Clause License
Keywords: analytics,ml,statistics,causal inference
Classifier: Environment :: Console
Classifier: Operating System :: OS Independent
Classifier: Programming Language :: Python :: 3
Classifier: Topic :: Scientific/Engineering :: Information Analysis
Requires-Python: >=3.9
License-File: LICENSE
Requires-Dist: pyarrow
Requires-Dist: click
